<?xml version="1.0" encoding="UTF-8" standalone="yes"?>
<w:styles xmlns:r="http://schemas.openxmlformats.org/officeDocument/2006/relationships" xmlns:w="http://schemas.openxmlformats.org/wordprocessingml/2006/main"><w:docDefaults><w:rPrDefault><w:rPr><w:rFonts w:asciiTheme="minorHAnsi" w:eastAsiaTheme="minorEastAsia" w:hAnsiTheme="minorHAnsi" w:cstheme="minorBidi"/><w:sz w:val="22"/><w:szCs w:val="22"/><w:lang w:val="en-GB" w:eastAsia="en-GB" w:bidi="ar-SA"/></w:rPr></w:rPrDefault><w:pPrDefault><w:pPr><w:spacing w:after="200" w:line="276" w:lineRule="auto"/></w:pPr></w:pPrDefault></w:docDefaults><w:latentStyles w:defLockedState="0" w:defUIPriority="99" w:defSemiHidden="1" w:defUnhideWhenUsed="1" w:defQFormat="0" w:count="267"><w:lsdException w:name="Normal" w:semiHidden="0" w:uiPriority="0" w:unhideWhenUsed="0" w:qFormat="1"/><w:lsdException w:name="heading 1" w:semiHidden="0" w:uiPriority="9" w:unhideWhenUsed="0" w:qFormat="1"/><w:lsdException w:name="heading 2" w:uiPriority="9" w:qFormat="1"/><w:lsdException w:name="heading 3" w:uiPriority="9" w:qFormat="1"/><w:lsdException w:name="heading 4" w:uiPriority="9" w:qFormat="1"/><w:lsdException w:name="heading 5" w:uiPriority="9" w:qFormat="1"/><w:lsdException w:name="heading 6" w:uiPriority="9" w:qFormat="1"/><w:lsdException w:name="heading 7" w:uiPriority="9" w:qFormat="1"/><w:lsdException w:name="heading 8" w:uiPriority="9" w:qFormat="1"/><w:lsdException w:name="heading 9" w:uiPriority="9" w:qFormat="1"/><w:lsdException w:name="toc 1" w:uiPriority="39"/><w:lsdException w:name="toc 2" w:uiPriority="39"/><w:lsdException w:name="toc 3" w:uiPriority="39"/><w:lsdException w:name="toc 4" w:uiPriority="39"/><w:lsdException w:name="toc 5" w:uiPriority="39"/><w:lsdException w:name="toc 6" w:uiPriority="39"/><w:lsdException w:name="toc 7" w:uiPriority="39"/><w:lsdException w:name="toc 8" w:uiPriority="39"/><w:lsdException w:name="toc 9" w:uiPriority="39"/><w:lsdException w:name="caption" w:uiPriority="35" w:qFormat="1"/><w:lsdException w:name="Title" w:semiHidden="0" w:uiPriority="10" w:unhideWhenUsed="0" w:qFormat="1"/><w:lsdException w:name="Default Paragraph Font" w:uiPriority="1"/><w:lsdException w:name="Subtitle" w:semiHidden="0" w:uiPriority="11" w:unhideWhenUsed="0" w:qFormat="1"/><w:lsdException w:name="Strong" w:semiHidden="0" w:uiPriority="22" w:unhideWhenUsed="0" w:qFormat="1"/><w:lsdException w:name="Emphasis" w:semiHidden="0" w:uiPriority="20" w:unhideWhenUsed="0" w:qFormat="1"/><w:lsdException w:name="Table Grid" w:semiHidden="0" w:uiPriority="59" w:unhideWhenUsed="0"/><w:lsdException w:name="Placeholder Text" w:unhideWhenUsed="0"/><w:lsdException w:name="No Spacing" w:semiHidden="0" w:uiPriority="1" w:unhideWhenUsed="0" w:qFormat="1"/><w:lsdException w:name="Light Shading" w:semiHidden="0" w:uiPriority="60" w:unhideWhenUsed="0"/><w:lsdException w:name="Light List" w:semiHidden="0" w:uiPriority="61" w:unhideWhenUsed="0"/><w:lsdException w:name="Light Grid" w:semiHidden="0" w:uiPriority="62" w:unhideWhenUsed="0"/><w:lsdException w:name="Medium Shading 1" w:semiHidden="0" w:uiPriority="63" w:unhideWhenUsed="0"/><w:lsdException w:name="Medium Shading 2" w:semiHidden="0" w:uiPriority="64" w:unhideWhenUsed="0"/><w:lsdException w:name="Medium List 1" w:semiHidden="0" w:uiPriority="65" w:unhideWhenUsed="0"/><w:lsdException w:name="Medium List 2" w:semiHidden="0" w:uiPriority="66" w:unhideWhenUsed="0"/><w:lsdException w:name="Medium Grid 1" w:semiHidden="0" w:uiPriority="67" w:unhideWhenUsed="0"/><w:lsdException w:name="Medium Grid 2" w:semiHidden="0" w:uiPriority="68" w:unhideWhenUsed="0"/><w:lsdException w:name="Medium Grid 3" w:semiHidden="0" w:uiPriority="69" w:unhideWhenUsed="0"/><w:lsdException w:name="Dark List" w:semiHidden="0" w:uiPriority="70" w:unhideWhenUsed="0"/><w:lsdException w:name="Colorful Shading" w:semiHidden="0" w:uiPriority="71" w:unhideWhenUsed="0"/><w:lsdException w:name="Colorful List" w:semiHidden="0" w:uiPriority="72" w:unhideWhenUsed="0"/><w:lsdException w:name="Colorful Grid" w:semiHidden="0" w:uiPriority="73" w:unhideWhenUsed="0"/><w:lsdException w:name="Light Shading Accent 1" w:semiHidden="0" w:uiPriority="60" w:unhideWhenUsed="0"/><w:lsdException w:name="Light List Accent 1" w:semiHidden="0" w:uiPriority="61" w:unhideWhenUsed="0"/><w:lsdException w:name="Light Grid Accent 1" w:semiHidden="0" w:uiPriority="62" w:unhideWhenUsed="0"/><w:lsdException w:name="Medium Shading 1 Accent 1" w:semiHidden="0" w:uiPriority="63" w:unhideWhenUsed="0"/><w:lsdException w:name="Medium Shading 2 Accent 1" w:semiHidden="0" w:uiPriority="64" w:unhideWhenUsed="0"/><w:lsdException w:name="Medium List 1 Accent 1" w:semiHidden="0" w:uiPriority="65" w:unhideWhenUsed="0"/><w:lsdException w:name="Revision" w:unhideWhenUsed="0"/><w:lsdException w:name="List Paragraph" w:semiHidden="0" w:uiPriority="34" w:unhideWhenUsed="0" w:qFormat="1"/><w:lsdException w:name="Quote" w:semiHidden="0" w:uiPriority="29" w:unhideWhenUsed="0" w:qFormat="1"/><w:lsdException w:name="Intense Quote" w:semiHidden="0" w:uiPriority="30" w:unhideWhenUsed="0" w:qFormat="1"/><w:lsdException w:name="Medium List 2 Accent 1" w:semiHidden="0" w:uiPriority="66" w:unhideWhenUsed="0"/><w:lsdException w:name="Medium Grid 1 Accent 1" w:semiHidden="0" w:uiPriority="67" w:unhideWhenUsed="0"/><w:lsdException w:name="Medium Grid 2 Accent 1" w:semiHidden="0" w:uiPriority="68" w:unhideWhenUsed="0"/><w:lsdException w:name="Medium Grid 3 Accent 1" w:semiHidden="0" w:uiPriority="69" w:unhideWhenUsed="0"/><w:lsdException w:name="Dark List Accent 1" w:semiHidden="0" w:uiPriority="70" w:unhideWhenUsed="0"/><w:lsdException w:name="Colorful Shading Accent 1" w:semiHidden="0" w:uiPriority="71" w:unhideWhenUsed="0"/><w:lsdException w:name="Colorful List Accent 1" w:semiHidden="0" w:uiPriority="72" w:unhideWhenUsed="0"/><w:lsdException w:name="Colorful Grid Accent 1" w:semiHidden="0" w:uiPriority="73" w:unhideWhenUsed="0"/><w:lsdException w:name="Light Shading Accent 2" w:semiHidden="0" w:uiPriority="60" w:unhideWhenUsed="0"/><w:lsdException w:name="Light List Accent 2" w:semiHidden="0" w:uiPriority="61" w:unhideWhenUsed="0"/><w:lsdException w:name="Light Grid Accent 2" w:semiHidden="0" w:uiPriority="62" w:unhideWhenUsed="0"/><w:lsdException w:name="Medium Shading 1 Accent 2" w:semiHidden="0" w:uiPriority="63" w:unhideWhenUsed="0"/><w:lsdException w:name="Medium Shading 2 Accent 2" w:semiHidden="0" w:uiPriority="64" w:unhideWhenUsed="0"/><w:lsdException w:name="Medium List 1 Accent 2" w:semiHidden="0" w:uiPriority="65" w:unhideWhenUsed="0"/><w:lsdException w:name="Medium List 2 Accent 2" w:semiHidden="0" w:uiPriority="66" w:unhideWhenUsed="0"/><w:lsdException w:name="Medium Grid 1 Accent 2" w:semiHidden="0" w:uiPriority="67" w:unhideWhenUsed="0"/><w:lsdException w:name="Medium Grid 2 Accent 2" w:semiHidden="0" w:uiPriority="68" w:unhideWhenUsed="0"/><w:lsdException w:name="Medium Grid 3 Accent 2" w:semiHidden="0" w:uiPriority="69" w:unhideWhenUsed="0"/><w:lsdException w:name="Dark List Accent 2" w:semiHidden="0" w:uiPriority="70" w:unhideWhenUsed="0"/><w:lsdException w:name="Colorful Shading Accent 2" w:semiHidden="0" w:uiPriority="71" w:unhideWhenUsed="0"/><w:lsdException w:name="Colorful List Accent 2" w:semiHidden="0" w:uiPriority="72" w:unhideWhenUsed="0"/><w:lsdException w:name="Colorful Grid Accent 2" w:semiHidden="0" w:uiPriority="73" w:unhideWhenUsed="0"/><w:lsdException w:name="Light Shading Accent 3" w:semiHidden="0" w:uiPriority="60" w:unhideWhenUsed="0"/><w:lsdException w:name="Light List Accent 3" w:semiHidden="0" w:uiPriority="61" w:unhideWhenUsed="0"/><w:lsdException w:name="Light Grid Accent 3" w:semiHidden="0" w:uiPriority="62" w:unhideWhenUsed="0"/><w:lsdException w:name="Medium Shading 1 Accent 3" w:semiHidden="0" w:uiPriority="63" w:unhideWhenUsed="0"/><w:lsdException w:name="Medium Shading 2 Accent 3" w:semiHidden="0" w:uiPriority="64" w:unhideWhenUsed="0"/><w:lsdException w:name="Medium List 1 Accent 3" w:semiHidden="0" w:uiPriority="65" w:unhideWhenUsed="0"/><w:lsdException w:name="Medium List 2 Accent 3" w:semiHidden="0" w:uiPriority="66" w:unhideWhenUsed="0"/><w:lsdException w:name="Medium Grid 1 Accent 3" w:semiHidden="0" w:uiPriority="67" w:unhideWhenUsed="0"/><w:lsdException w:name="Medium Grid 2 Accent 3" w:semiHidden="0" w:uiPriority="68" w:unhideWhenUsed="0"/><w:lsdException w:name="Medium Grid 3 Accent 3" w:semiHidden="0" w:uiPriority="69" w:unhideWhenUsed="0"/><w:lsdException w:name="Dark List Accent 3" w:semiHidden="0" w:uiPriority="70" w:unhideWhenUsed="0"/><w:lsdException w:name="Colorful Shading Accent 3" w:semiHidden="0" w:uiPriority="71" w:unhideWhenUsed="0"/><w:lsdException w:name="Colorful List Accent 3" w:semiHidden="0" w:uiPriority="72" w:unhideWhenUsed="0"/><w:lsdException w:name="Colorful Grid Accent 3" w:semiHidden="0" w:uiPriority="73" w:unhideWhenUsed="0"/><w:lsdException w:name="Light Shading Accent 4" w:semiHidden="0" w:uiPriority="60" w:unhideWhenUsed="0"/><w:lsdException w:name="Light List Accent 4" w:semiHidden="0" w:uiPriority="61" w:unhideWhenUsed="0"/><w:lsdException w:name="Light Grid Accent 4" w:semiHidden="0" w:uiPriority="62" w:unhideWhenUsed="0"/><w:lsdException w:name="Medium Shading 1 Accent 4" w:semiHidden="0" w:uiPriority="63" w:unhideWhenUsed="0"/><w:lsdException w:name="Medium Shading 2 Accent 4" w:semiHidden="0" w:uiPriority="64" w:unhideWhenUsed="0"/><w:lsdException w:name="Medium List 1 Accent 4" w:semiHidden="0" w:uiPriority="65" w:unhideWhenUsed="0"/><w:lsdException w:name="Medium List 2 Accent 4" w:semiHidden="0" w:uiPriority="66" w:unhideWhenUsed="0"/><w:lsdException w:name="Medium Grid 1 Accent 4" w:semiHidden="0" w:uiPriority="67" w:unhideWhenUsed="0"/><w:lsdException w:name="Medium Grid 2 Accent 4" w:semiHidden="0" w:uiPriority="68" w:unhideWhenUsed="0"/><w:lsdException w:name="Medium Grid 3 Accent 4" w:semiHidden="0" w:uiPriority="69" w:unhideWhenUsed="0"/><w:lsdException w:name="Dark List Accent 4" w:semiHidden="0" w:uiPriority="70" w:unhideWhenUsed="0"/><w:lsdException w:name="Colorful Shading Accent 4" w:semiHidden="0" w:uiPriority="71" w:unhideWhenUsed="0"/><w:lsdException w:name="Colorful List Accent 4" w:semiHidden="0" w:uiPriority="72" w:unhideWhenUsed="0"/><w:lsdException w:name="Colorful Grid Accent 4" w:semiHidden="0" w:uiPriority="73" w:unhideWhenUsed="0"/><w:lsdException w:name="Light Shading Accent 5" w:semiHidden="0" w:uiPriority="60" w:unhideWhenUsed="0"/><w:lsdException w:name="Light List Accent 5" w:semiHidden="0" w:uiPriority="61" w:unhideWhenUsed="0"/><w:lsdException w:name="Light Grid Accent 5" w:semiHidden="0" w:uiPriority="62" w:unhideWhenUsed="0"/><w:lsdException w:name="Medium Shading 1 Accent 5" w:semiHidden="0" w:uiPriority="63" w:unhideWhenUsed="0"/><w:lsdException w:name="Medium Shading 2 Accent 5" w:semiHidden="0" w:uiPriority="64" w:unhideWhenUsed="0"/><w:lsdException w:name="Medium List 1 Accent 5" w:semiHidden="0" w:uiPriority="65" w:unhideWhenUsed="0"/><w:lsdException w:name="Medium List 2 Accent 5" w:semiHidden="0" w:uiPriority="66" w:unhideWhenUsed="0"/><w:lsdException w:name="Medium Grid 1 Accent 5" w:semiHidden="0" w:uiPriority="67" w:unhideWhenUsed="0"/><w:lsdException w:name="Medium Grid 2 Accent 5" w:semiHidden="0" w:uiPriority="68" w:unhideWhenUsed="0"/><w:lsdException w:name="Medium Grid 3 Accent 5" w:semiHidden="0" w:uiPriority="69" w:unhideWhenUsed="0"/><w:lsdException w:name="Dark List Accent 5" w:semiHidden="0" w:uiPriority="70" w:unhideWhenUsed="0"/><w:lsdException w:name="Colorful Shading Accent 5" w:semiHidden="0" w:uiPriority="71" w:unhideWhenUsed="0"/><w:lsdException w:name="Colorful List Accent 5" w:semiHidden="0" w:uiPriority="72" w:unhideWhenUsed="0"/><w:lsdException w:name="Colorful Grid Accent 5" w:semiHidden="0" w:uiPriority="73" w:unhideWhenUsed="0"/><w:lsdException w:name="Light Shading Accent 6" w:semiHidden="0" w:uiPriority="60" w:unhideWhenUsed="0"/><w:lsdException w:name="Light List Accent 6" w:semiHidden="0" w:uiPriority="61" w:unhideWhenUsed="0"/><w:lsdException w:name="Light Grid Accent 6" w:semiHidden="0" w:uiPriority="62" w:unhideWhenUsed="0"/><w:lsdException w:name="Medium Shading 1 Accent 6" w:semiHidden="0" w:uiPriority="63" w:unhideWhenUsed="0"/><w:lsdException w:name="Medium Shading 2 Accent 6" w:semiHidden="0" w:uiPriority="64" w:unhideWhenUsed="0"/><w:lsdException w:name="Medium List 1 Accent 6" w:semiHidden="0" w:uiPriority="65" w:unhideWhenUsed="0"/><w:lsdException w:name="Medium List 2 Accent 6" w:semiHidden="0" w:uiPriority="66" w:unhideWhenUsed="0"/><w:lsdException w:name="Medium Grid 1 Accent 6" w:semiHidden="0" w:uiPriority="67" w:unhideWhenUsed="0"/><w:lsdException w:name="Medium Grid 2 Accent 6" w:semiHidden="0" w:uiPriority="68" w:unhideWhenUsed="0"/><w:lsdException w:name="Medium Grid 3 Accent 6" w:semiHidden="0" w:uiPriority="69" w:unhideWhenUsed="0"/><w:lsdException w:name="Dark List Accent 6" w:semiHidden="0" w:uiPriority="70" w:unhideWhenUsed="0"/><w:lsdException w:name="Colorful Shading Accent 6" w:semiHidden="0" w:uiPriority="71" w:unhideWhenUsed="0"/><w:lsdException w:name="Colorful List Accent 6" w:semiHidden="0" w:uiPriority="72" w:unhideWhenUsed="0"/><w:lsdException w:name="Colorful Grid Accent 6" w:semiHidden="0" w:uiPriority="73" w:unhideWhenUsed="0"/><w:lsdException w:name="Subtle Emphasis" w:semiHidden="0" w:uiPriority="19" w:unhideWhenUsed="0" w:qFormat="1"/><w:lsdException w:name="Intense Emphasis" w:semiHidden="0" w:uiPriority="21" w:unhideWhenUsed="0" w:qFormat="1"/><w:lsdException w:name="Subtle Reference" w:semiHidden="0" w:uiPriority="31" w:unhideWhenUsed="0" w:qFormat="1"/><w:lsdException w:name="Intense Reference" w:semiHidden="0" w:uiPriority="32" w:unhideWhenUsed="0" w:qFormat="1"/><w:lsdException w:name="Book Title" w:semiHidden="0" w:uiPriority="33" w:unhideWhenUsed="0" w:qFormat="1"/><w:lsdException w:name="Bibliography" w:uiPriority="37"/><w:lsdException w:name="TOC Heading" w:uiPriority="39" w:qFormat="1"/></w:latentStyles><w:style w:type="paragraph" w:default="1" w:styleId="Normal"><w:name w:val="Normal"/><w:qFormat/><w:rsid w:val="006F7435"/></w:style><w:style w:type="character" w:default="1" w:styleId="DefaultParagraphFont"><w:name w:val="Default Paragraph Font"/><w:uiPriority w:val="1"/><w:semiHidden/><w:unhideWhenUsed/></w:style><w:style w:type="table" w:default="1" w:styleId="TableNormal"><w:name w:val="Normal Table"/><w:uiPriority w:val="99"/><w:semiHidden/><w:unhideWhenUsed/><w:qFormat/><w:tblPr><w:tblInd w:w="0" w:type="dxa"/><w:tblCellMar><w:top w:w="0" w:type="dxa"/><w:left w:w="108" w:type="dxa"/><w:bottom w:w="0" w:type="dxa"/><w:right w:w="108" w:type="dxa"/></w:tblCellMar></w:tblPr></w:style><w:style w:type="numbering" w:default="1" w:styleId="NoList"><w:name w:val="No List"/><w:uiPriority w:val="99"/><w:semiHidden/><w:unhideWhenUsed/></w:style><w:style w:type="paragraph" w:customStyle="1" w:styleId="DEAD309776124EF8BB8EA85E7ED551A7"><w:name w:val="DEAD309776124EF8BB8EA85E7ED551A7"/><w:rsid w:val="006F7435"/></w:style><w:style w:type="paragraph" w:customStyle="1" w:styleId="35C8631395C24AD5A31B37DD4DB65F22"><w:name w:val="35C8631395C24AD5A31B37DD4DB65F22"/><w:rsid w:val="006F7435"/></w:style><w:style w:type="character" w:styleId="PlaceholderText"><w:name w:val="Placeholder Text"/><w:basedOn w:val="DefaultParagraphFont"/><w:uiPriority w:val="99"/><w:semiHidden/><w:rsid w:val="00A04785"/><w:rPr><w:color w:val="808080"/></w:rPr></w:style><w:style w:type="paragraph" w:customStyle="1" w:styleId="8CDF56F367F442AE9EC5C24ACA6EF567"><w:name w:val="8CDF56F367F442AE9EC5C24ACA6EF567"/><w:rsid w:val="006F7435"/></w:style><w:style w:type="paragraph" w:customStyle="1" w:styleId="697EEB59B6354BE48246695680D97C8B"><w:name w:val="697EEB59B6354BE48246695680D97C8B"/><w:rsid w:val="006F7435"/></w:style><w:style w:type="paragraph" w:customStyle="1" w:styleId="ABDA498A375E482888C648F2E08BDFE4"><w:name w:val="ABDA498A375E482888C648F2E08BDFE4"/><w:rsid w:val="006F7435"/></w:style><w:style w:type="paragraph" w:customStyle="1" w:styleId="8C8382C5B0D444849DAF06A5E806ED71"><w:name w:val="8C8382C5B0D444849DAF06A5E806ED71"/><w:rsid w:val="006F7435"/></w:style><w:style w:type="paragraph" w:customStyle="1" w:styleId="6699B3B5240349DC8F5467B33E2935AA"><w:name w:val="6699B3B5240349DC8F5467B33E2935AA"/><w:rsid w:val="006F7435"/></w:style><w:style w:type="paragraph" w:customStyle="1" w:styleId="2D90337E4581441DA667DF8F2BFF98C1"><w:name w:val="2D90337E4581441DA667DF8F2BFF98C1"/><w:rsid w:val="006F7435"/></w:style><w:style w:type="paragraph" w:customStyle="1" w:styleId="A46C06C807684D189A50154C73FB106D"><w:name w:val="A46C06C807684D189A50154C73FB106D"/><w:rsid w:val="006F7435"/></w:style><w:style w:type="paragraph" w:customStyle="1" w:styleId="06996FC8B0B742E38BD17121FD17EF41"><w:name w:val="06996FC8B0B742E38BD17121FD17EF41"/><w:rsid w:val="006F7435"/></w:style><w:style w:type="paragraph" w:customStyle="1" w:styleId="F1C0693F55C1440C84034AB1A5C7275F"><w:name w:val="F1C0693F55C1440C84034AB1A5C7275F"/><w:rsid w:val="006F7435"/></w:style><w:style w:type="paragraph" w:customStyle="1" w:styleId="FE67EF48687D441792E2FDE9215D50D2"><w:name w:val="FE67EF48687D441792E2FDE9215D50D2"/><w:rsid w:val="006F7435"/></w:style><w:style w:type="paragraph" w:customStyle="1" w:styleId="426C9F658C03407D8D075CF7512D6092"><w:name w:val="426C9F658C03407D8D075CF7512D6092"/><w:rsid w:val="006F7435"/></w:style><w:style w:type="paragraph" w:customStyle="1" w:styleId="A65928B9A94543D28002040F1E080A68"><w:name w:val="A65928B9A94543D28002040F1E080A68"/><w:rsid w:val="006F7435"/></w:style><w:style w:type="paragraph" w:customStyle="1" w:styleId="BC498DF442004DB0A5611B69683EA86D"><w:name w:val="BC498DF442004DB0A5611B69683EA86D"/><w:rsid w:val="006F7435"/></w:style><w:style w:type="paragraph" w:customStyle="1" w:styleId="69C28C1CB416430184B7951281D9DA7B"><w:name w:val="69C28C1CB416430184B7951281D9DA7B"/><w:rsid w:val="006F7435"/></w:style><w:style w:type="paragraph" w:customStyle="1" w:styleId="712910D742764C5FBAADE3CC52E28220"><w:name w:val="712910D742764C5FBAADE3CC52E28220"/><w:rsid w:val="006F7435"/></w:style><w:style w:type="paragraph" w:customStyle="1" w:styleId="6C3EFC9641524D6091A1AB1D1F711A84"><w:name w:val="6C3EFC9641524D6091A1AB1D1F711A84"/><w:rsid w:val="006F7435"/></w:style><w:style w:type="paragraph" w:customStyle="1" w:styleId="2734C328D3754E749DBC55FB463BBFD1"><w:name w:val="2734C328D3754E749DBC55FB463BBFD1"/><w:rsid w:val="006F7435"/></w:style><w:style w:type="paragraph" w:customStyle="1" w:styleId="C8CCDAE1E2A14F35BFE823B70A67AE53"><w:name w:val="C8CCDAE1E2A14F35BFE823B70A67AE53"/><w:rsid w:val="006F7435"/></w:style><w:style w:type="paragraph" w:customStyle="1" w:styleId="A1AB317C1D9A4AF08EB2DB242A49E7CD"><w:name w:val="A1AB317C1D9A4AF08EB2DB242A49E7CD"/><w:rsid w:val="006F7435"/></w:style><w:style w:type="paragraph" w:customStyle="1" w:styleId="52FC66BD16DA4022BA9EB9C790B822C2"><w:name w:val="52FC66BD16DA4022BA9EB9C790B822C2"/><w:rsid w:val="006F7435"/></w:style><w:style w:type="paragraph" w:customStyle="1" w:styleId="D8C6FD1D5FE24B1E807F61E1139693DE"><w:name w:val="D8C6FD1D5FE24B1E807F61E1139693DE"/><w:rsid w:val="006F7435"/></w:style><w:style w:type="paragraph" w:customStyle="1" w:styleId="C257BA482C054316BC3D6E0587906BE4"><w:name w:val="C257BA482C054316BC3D6E0587906BE4"/><w:rsid w:val="006F7435"/></w:style><w:style w:type="paragraph" w:customStyle="1" w:styleId="B38D1570548D492D8C760A00D66D79E8"><w:name w:val="B38D1570548D492D8C760A00D66D79E8"/><w:rsid w:val="006F7435"/></w:style><w:style w:type="paragraph" w:customStyle="1" w:styleId="ADF5AD4F887849A9A999B6F13FE78565"><w:name w:val="ADF5AD4F887849A9A999B6F13FE78565"/><w:rsid w:val="006F7435"/></w:style><w:style w:type="paragraph" w:customStyle="1" w:styleId="DD3C7A27E2A44B58881062281C3EA369"><w:name w:val="DD3C7A27E2A44B58881062281C3EA369"/><w:rsid w:val="006F7435"/></w:style><w:style w:type="paragraph" w:customStyle="1" w:styleId="3CFFC4526E5748DBB4F84B6BE31A563B"><w:name w:val="3CFFC4526E5748DBB4F84B6BE31A563B"/><w:rsid w:val="006F7435"/></w:style><w:style w:type="paragraph" w:customStyle="1" w:styleId="1EEDA626DF0B4C659B421A35660D6645"><w:name w:val="1EEDA626DF0B4C659B421A35660D6645"/><w:rsid w:val="006F7435"/></w:style><w:style w:type="paragraph" w:customStyle="1" w:styleId="B44FC7F4A5B34E58B171D76DB28A42DE"><w:name w:val="B44FC7F4A5B34E58B171D76DB28A42DE"/><w:rsid w:val="006F7435"/></w:style><w:style w:type="paragraph" w:customStyle="1" w:styleId="CF247496BE26413F984D98AC06BAFA7B"><w:name w:val="CF247496BE26413F984D98AC06BAFA7B"/><w:rsid w:val="00A6378A"/></w:style></w:styles>